digimind/__init__.py
digimind/test.py
digimind-0.0.3.dist-info/METADATA
digimind-0.0.3.dist-info/WHEEL
digimind-0.0.3.dist-info/top_level.txt
digimind-0.0.3.dist-info/RECORD
