Metadata-Version: 2.1
Name: digimind
Version: 0.0.3
Summary: DigiMind - Remaining Cycle Time Predictor
Author: DigiMind Team
License: MIT
